scripts/__init__.py
scripts/geom_converter.py
geometry_converter-1.0.dist-info/METADATA
geometry_converter-1.0.dist-info/WHEEL
geometry_converter-1.0.dist-info/entry_points.txt
geometry_converter-1.0.dist-info/top_level.txt
geometry_converter-1.0.dist-info/RECORD
