Metadata-Version: 2.1
Name: geometry-converter
Version: 1.0
Summary: Library to convert between different Geometry formats
Home-page: https://github.com/Alok-Senapati/MapsScripts
Author: Alok Senapati
Author-email: aloksenapati470@gmail.com
License: MIT
Requires-Dist: numpy ==1.26.4
Requires-Dist: shapely ==1.7.1
